{"timestamp": 1774390632391499000, "uuid": "9e78cd33-64a1-498c-b0d9-6bd24cda246e", "event_type": "COMMENT", "env_id": "c3d2c46e-df9e-40c4-8014-5e8c9fdf3cc1", "author": "Joe Oakhart", "data": {"body": "## Description\nWrite a failing regression test (tests/scripts/test-v2-docs-cleanup.sh) that will verify v2 reference cleanup in story 985e-0421.\n\n## TDD Requirement\nCreate test file and RUN it to confirm it FAILS (RED) against current codebase before any implementation.\n\n## Implementation Steps\n1. Create tests/scripts/test-v2-docs-cleanup.sh following patterns from tests/scripts/test-docs-config-refs.sh\n2. Source tests/lib/assert.sh\n3. Include these test functions:\n   - test_rollback_procedure_deleted: assert ROLLBACK-PROCEDURE.md does not exist\n   - test_no_tk_wrapper_row_in_cli_reference: grep for 'the tk wrapper: `tk' should return no matches in ticket-cli-reference.md\n   - test_no_tk_sync_ref_in_cli_reference: sync section does not say 'via the tk wrapper'\n   - test_no_tk_legacy_archive_ref_in_cli_reference: archive section does not reference 'tk move-to-archive-directory'\n   - test_no_tickets_dir_v2_in_worktree_guide: WORKTREE-GUIDE.md does not say '.tickets/ which is git-tracked and shared'\n   - test_no_issue_tracker_create_cmd_section_in_config_ref: CONFIGURATION-REFERENCE.md has no '### `issue_tracker.create_cmd`' heading\n   - test_no_tk_script_in_used_by_fields: CONFIGURATION-REFERENCE.md has no 'the tk script' in Used by fields\n   - test_no_tk_in_sync_contract: ticket-sync-events-contract.md has no 'the tk wrapper'\n   - test_no_issue_tracker_in_precommit_wrapper: PRE-COMMIT-TIMEOUT-WRAPPER.md has no 'issue_tracker.create_cmd'\n   - test_no_issue_tracker_in_example_conf: dso-config.example.conf has no 'issue_tracker.create_cmd='\n   - test_no_tk_wrapper_in_validate_work_skill: validate-work/SKILL.md has no 'the tk wrapper' or 'tk commands'\n   - test_no_tk_wrapper_in_tickets_health_prompt: validate-work/prompts/tickets-health.md has no 'the tk wrapper'\n   - test_no_v2_tickets_comments_in_merge_to_main: merge-to-main.sh comment lines do not contain '.tickets/*.md' patterns\n4. Run: bash tests/scripts/test-v2-docs-cleanup.sh \u2014 expect FAILED output (RED)\n\n## File Impact\n- CREATE: tests/scripts/test-v2-docs-cleanup.sh\n\n## test-exempt justification\nN/A \u2014 this task creates the regression test.\n\n## Acceptance Criteria\n- [ ] tests/scripts/test-v2-docs-cleanup.sh exists and is executable\n  Verify: test -x $(git rev-parse --show-toplevel)/tests/scripts/test-v2-docs-cleanup.sh\n- [ ] Test runs and produces FAILED results against current codebase (RED)\n  Verify: bash $(git rev-parse --show-toplevel)/tests/scripts/test-v2-docs-cleanup.sh 2>&1; test $? -ne 0\n- [ ] ruff check passes (exit 0)\n  Verify: ruff check plugins/dso/scripts/*.py tests/**/*.py\n- [ ] ruff format --check passes (exit 0)\n  Verify: ruff format --check plugins/dso/scripts/*.py tests/**/*.py\n- [ ] .test-index entries added mapping each doc source file to this test\n  Verify: grep -q 'test-v2-docs-cleanup.sh' $(git rev-parse --show-toplevel)/.test-index"}}