{"event_type": "CREATE", "env_id": "", "jira_key": "OP-32", "local_id": "jira-op-32", "timestamp": 1774319047, "run_id": "23469985247", "data": {"jira_key": "OP-32", "fields": {"assignee": {"accountId": "70121:53379492-cd2a-4a4d-acd0-8217d3c8d8d8", "accountType": "atlassian", "active": true, "avatarUrls": {"16x16": "https://avatar-management--avatars.us-west-2.prod.public.atl-paas.net/70121:53379492-cd2a-4a4d-acd0-8217d3c8d8d8/b7ab5b5e-47cc-49a3-bec2-4ba842a0070c/16", "24x24": "https://avatar-management--avatars.us-west-2.prod.public.atl-paas.net/70121:53379492-cd2a-4a4d-acd0-8217d3c8d8d8/b7ab5b5e-47cc-49a3-bec2-4ba842a0070c/24", "32x32": "https://avatar-management--avatars.us-west-2.prod.public.atl-paas.net/70121:53379492-cd2a-4a4d-acd0-8217d3c8d8d8/b7ab5b5e-47cc-49a3-bec2-4ba842a0070c/32", "48x48": "https://avatar-management--avatars.us-west-2.prod.public.atl-paas.net/70121:53379492-cd2a-4a4d-acd0-8217d3c8d8d8/b7ab5b5e-47cc-49a3-bec2-4ba842a0070c/48"}, "displayName": "Barbara Ayala", "self": "https://jira-prod-us-51-as-2.prod.atl-paas.net/rest/api/3/user?accountId=70121%3A53379492-cd2a-4a4d-acd0-8217d3c8d8d8", "timeZone": "America/New_York"}, "issuetype": {"avatarId": 10318, "description": "A small, distinct piece of work.", "entityId": "68b0a678-12e2-446f-8aa2-e0f236f7746b", "hierarchyLevel": 0, "iconUrl": "https://jira-prod-us-51-as-2.prod.atl-paas.net/rest/api/2/universal_avatar/view/type/issuetype/avatar/10318?size=medium", "id": "10290", "name": "Task", "self": "https://jira-prod-us-51-as-2.prod.atl-paas.net/rest/api/3/issuetype/10290", "subtask": false}, "priority": {"iconUrl": "https://jira-prod-us-51-as-2.prod.atl-paas.net/images/icons/priorities/medium_new.svg", "id": "3", "name": "Medium", "self": "https://jira-prod-us-51-as-2.prod.atl-paas.net/rest/api/3/priority/3"}, "status": {"description": "", "iconUrl": "https://jira-prod-us-51-as-2.prod.atl-paas.net/", "id": "10541", "name": "IN PROGRESS", "self": "https://jira-prod-us-51-as-2.prod.atl-paas.net/rest/api/3/status/10541", "statusCategory": {"colorName": "yellow", "id": 4, "key": "indeterminate", "name": "In Progress", "self": "https://jira-prod-us-51-as-2.prod.atl-paas.net/rest/api/3/statuscategory/4"}}, "summary": "Get team cleared on cybersecurity training"}}}