{"timestamp": 1774647832744982000, "uuid": "e63d8e8f-116c-4c3e-b8a1-1b48464991a1", "event_type": "COMMENT", "env_id": "c3d2c46e-df9e-40c4-8014-5e8c9fdf3cc1", "author": "Joe Oakhart", "data": {"body": "## Description\n\n**What**: Extract brainstorm's inline scrutiny steps (gap analysis, web research, scenario analysis, fidelity review with feasibility trigger) into a shared workflow invocable by both /brainstorm and /roadmap\n**Why**: Roadmap currently produces lower-fidelity specs because it lacks these scrutiny layers. Extracting them enables both skills to produce equivalent-quality output\n**Scope**:\n- IN: Create shared scrutiny pipeline workflow; update /brainstorm to invoke the pipeline instead of inline logic; pipeline accepts a structured epic spec as input and produces a scrutiny report\n- OUT: Integrating the pipeline into /roadmap (Story 4); modifying scrutiny step behavior\n\n## Done Definitions\n\n- When this story is complete, /brainstorm produces scrutiny output via the shared pipeline and no scrutiny step definitions (gap analysis, web research, scenario analysis) remain inline in brainstorm's SKILL.md\n  \u2190 Satisfies: \"neither skill contains inline scrutiny logic\"\n- When this story is complete, unit tests written and passing for all new or modified logic\n  \u2190 Satisfies: TDD DoD\n\n## Considerations\n\n- [Maintainability] Brainstorm invokes reviewers via direct Task dispatch with validate-review-output.sh. Roadmap uses /dso:review-protocol. The shared pipeline must standardize on one invocation mechanism\n- [Scope] Brainstorm's gap analysis (Step 2.5) references user dialogue artifacts. When invoked from roadmap, the input shape differs. The pipeline must accept a generic structured input or the gap analysis step must adapt to the caller's context\n- [Reliability] Pipeline dispatches multiple sub-agents (red team, blue team, fidelity reviewers) \u2014 respect the 5-concurrent-sub-agent limit"}}