{"timestamp": 1774392210838809000, "uuid": "3aa2dbd8-b2ec-47a9-b6c4-8f1635f9b823", "event_type": "COMMENT", "env_id": "c3d2c46e-df9e-40c4-8014-5e8c9fdf3cc1", "author": "Joe Oakhart", "data": {"body": "## Adversarial Review Finding (accepted)\n\n**implementation-plan needs graceful degradation, not hard exit**: /dso:implementation-plan is legitimately invoked as a sub-agent from /dso:sprint. A hard \"exit immediately\" guard would break sprint's workflow entirely. implementation-plan should either be removed from the hard-exit guard list (it already has its own sub-agent handling in Step 6) or use a graceful degradation pattern like fix-bug instead of a hard exit. This must be resolved during guard pattern design.\n\n## Additional Consideration (adversarial review)\n\n- [Testing] Test file must support two guard variant patterns from the start: one for sub-agent dependent skills (Agent tool check) and one for user-interaction dependent skills (orchestrator signal phrase check). Story 2 adds the second variant \u2014 Story 1's test design must accommodate both."}}