{"event_type": "CREATE", "env_id": "", "jira_key": "VSDBP-21", "local_id": "jira-vsdbp-21", "timestamp": 1774319047, "run_id": "23469985247", "data": {"jira_key": "VSDBP-21", "fields": {"assignee": {"accountId": "712020:9f5806ba-2f16-40ca-8ec5-9ccbf4f0b932", "accountType": "atlassian", "active": true, "avatarUrls": {"16x16": "https://avatar-management--avatars.us-west-2.prod.public.atl-paas.net/712020:9f5806ba-2f16-40ca-8ec5-9ccbf4f0b932/326e4d05-a406-4100-863f-637d4c780525/16", "24x24": "https://avatar-management--avatars.us-west-2.prod.public.atl-paas.net/712020:9f5806ba-2f16-40ca-8ec5-9ccbf4f0b932/326e4d05-a406-4100-863f-637d4c780525/24", "32x32": "https://avatar-management--avatars.us-west-2.prod.public.atl-paas.net/712020:9f5806ba-2f16-40ca-8ec5-9ccbf4f0b932/326e4d05-a406-4100-863f-637d4c780525/32", "48x48": "https://avatar-management--avatars.us-west-2.prod.public.atl-paas.net/712020:9f5806ba-2f16-40ca-8ec5-9ccbf4f0b932/326e4d05-a406-4100-863f-637d4c780525/48"}, "displayName": "Terry Nichols", "self": "https://jira-prod-us-51-as-2.prod.atl-paas.net/rest/api/3/user?accountId=712020%3A9f5806ba-2f16-40ca-8ec5-9ccbf4f0b932", "timeZone": "America/Chicago"}, "issuetype": {"avatarId": 10316, "description": "A small piece of work that's part of a larger task.", "entityId": "cea9b827-7a36-4768-a51d-6298f00f9433", "hierarchyLevel": -1, "iconUrl": "https://jira-prod-us-51-as-2.prod.atl-paas.net/rest/api/2/universal_avatar/view/type/issuetype/avatar/10316?size=medium", "id": "12403", "name": "Sub-task", "self": "https://jira-prod-us-51-as-2.prod.atl-paas.net/rest/api/3/issuetype/12403", "subtask": true}, "priority": {"iconUrl": "https://jira-prod-us-51-as-2.prod.atl-paas.net/images/icons/priorities/medium_new.svg", "id": "3", "name": "Medium", "self": "https://jira-prod-us-51-as-2.prod.atl-paas.net/rest/api/3/priority/3"}, "status": {"description": "", "iconUrl": "https://jira-prod-us-51-as-2.prod.atl-paas.net/", "id": "13799", "name": "Done", "self": "https://jira-prod-us-51-as-2.prod.atl-paas.net/rest/api/3/status/13799", "statusCategory": {"colorName": "green", "id": 3, "key": "done", "name": "Done", "self": "https://jira-prod-us-51-as-2.prod.atl-paas.net/rest/api/3/statuscategory/3"}}, "summary": "Creat process / workflow diagrams for Agile Sprint Process and Delivery Reports"}}}