{"timestamp": 1776479830878240000, "uuid": "1c8bce93-f651-4ee6-b715-45366df8e61d", "event_type": "CREATE", "env_id": "c3d2c46e-df9e-40c4-8014-5e8c9fdf3cc1", "author": "Test", "data": {"ticket_type": "bug", "title": "[test-batched.sh]: --filter flag does not exist -> unknown option error on first use", "parent_id": "", "description": "## Incident Overview\nAttempted to run targeted tests using test-batched.sh --runner=bash --test-dir=tests/scripts --filter=<pattern>. The --filter flag does not exist in test-batched.sh, producing ERROR: Unknown option: --filter=...\n\n## Expected Behavior\ntest-batched.sh supports a --filter flag to run a subset of test files matching a pattern, similar to pytest -k.\n\n## Actual Behavior\nERROR: Unknown option: --filter=... \u2014 must fall back to running individual test files directly (bash tests/scripts/test-foo.sh).", "tags": [], "priority": 2, "assignee": "Test"}}