{"timestamp": 1775117514566746000, "uuid": "145cea23-884f-42d6-93aa-732b2a31d718", "event_type": "COMMENT", "env_id": "c3d2c46e-df9e-40c4-8014-5e8c9fdf3cc1", "author": "Test", "data": {"body": "CHECKPOINT COMPLETE: Two fixes applied to tests/hooks/test-behavioral-equivalence-allowlist.sh:\n\n1. BASELINE_HASH pre-computation: Moved hash_before computation outside the per-test helper. Was: 1 bash subprocess per file for hash_before \u00d7 10-12 tests = 10-12 extra invocations. Now: computed once after git init.\n\n2. Cache collision fix: compute-diff-hash.sh caches by git index mtime (seconds precision). When multiple tests run in <1s, consecutive index staging/unstaging operations share the same mtime \u2192 stale cache hits \u2192 wrong hashes returned. Fix: pass TMPDIR=<call-unique-dir> for each compute-diff-hash.sh invocation, giving each call an empty cache namespace.\n\n3. WORKFLOW_CONFIG_FILE + WORKFLOW_PLUGIN_ARTIFACTS_DIR: Set at init time to skip git-based config resolution and artifact dir discovery overhead in each invocation.\n\nResult: Test now runs in ~8-26s (consistently) vs. >73s timeout. All 39 assertions pass in 6/6 consecutive runs."}}