{"timestamp": 1775337803292899000, "uuid": "7511b0c8-9a77-40bf-a8bd-827baa4fbf0e", "event_type": "COMMENT", "env_id": "c3d2c46e-df9e-40c4-8014-5e8c9fdf3cc1", "author": "Test", "data": {"body": "## SC4 Clarification (added after implementation)\n\nThe original SC4 text reads: 'route to implementation-plan in epic-direct mode to create new tasks.'\n\nAfter implementation, the actual behavior is:\n\n**SC4 (as implemented)**: At epic validation before closure, if a failing success criterion's text does not match what the implementation actually does (intent gap), route to brainstorm with user confirmation. If the criterion is clear but implementation does not fully satisfy it (implementation gap), route to **Phase 7 Step 1 bug-task creation** \u2014 the gap-classification sub-agent emits ROUTING: implementation-plan as a routing signal label, and the sprint orchestrator responds by creating targeted bug tasks via the existing Phase 7 remediation flow. The orchestrator does NOT invoke /dso:implementation-plan as a separate skill for implementation_gap resolution. The distinction between intent_gap and implementation_gap is made by the gap-classification sub-agent (see plugins/dso/docs/contracts/gap-classification-output.md) by comparing the criterion text against actual codebase behavior.\n\nThis clarification reflects option (b) from the original epic design: revise the SC language to match the actual behavior rather than changing the implementation to invoke /dso:implementation-plan in epic-direct mode."}}