{"timestamp": 1774388874726895000, "uuid": "971d9d9d-d352-4054-a729-a46b8537b461", "event_type": "COMMENT", "env_id": "c3d2c46e-df9e-40c4-8014-5e8c9fdf3cc1", "author": "Joe Oakhart", "data": {"body": "## TDD Requirement\n\nWrite failing tests (RED state) for classify-task.sh v2 removal. These tests must FAIL on the current codebase.\n\n## Implementation Steps\n\n1. Add new test functions to tests/scripts/test-classify-task.sh:\n   - test_classify_task_no_use_v3_detection: assert grep -q '_use_v3' plugins/dso/scripts/classify-task.sh exits non-zero\n   - test_classify_task_no_TICKETS_DIR_branch: assert grep -q '\\.tickets/$id\\.md' plugins/dso/scripts/classify-task.sh exits non-zero\n   - test_classify_task_no_tk_ready: assert grep -q 'tk ready' plugins/dso/scripts/classify-task.sh exits non-zero\n   - test_classify_task_no_tk_show: assert grep -q 'tk show' plugins/dso/scripts/classify-task.sh exits non-zero\n\n2. Verify each test fails on the current codebase (RED state).\n\n## Test File Notes\n- Existing test file: tests/scripts/test-classify-task.sh\n- Source: classify-task.sh \u2192 fuzzy match: classifytasksh\n- Test: test-classify-task.sh \u2192 fuzzy: testclassifytasksh \u2014 'classifytask' is substring. Fuzzy match OK, no .test-index needed.\n\n## Files Modified\n- tests/scripts/test-classify-task.sh (Edit \u2014 add test functions at end of file)\n\n## Acceptance Criteria\n- [ ] test_classify_task_no_use_v3_detection function exists in test-classify-task.sh\n  Verify: grep -q 'test_classify_task_no_use_v3_detection' $(git rev-parse --show-toplevel)/tests/scripts/test-classify-task.sh\n- [ ] test_classify_task_no_tk_ready function exists in test-classify-task.sh\n  Verify: grep -q 'test_classify_task_no_tk_ready' $(git rev-parse --show-toplevel)/tests/scripts/test-classify-task.sh\n- [ ] Tests FAIL on current codebase (RED state \u2014 _use_v3 still present)\n  Verify: { bash $(git rev-parse --show-toplevel)/tests/scripts/test-classify-task.sh 2>&1 | grep -q 'FAIL'; }\n- [ ] bash tests/run-all.sh passes (exit 0) \u2014 existing tests still pass\n  Verify: cd $(git rev-parse --show-toplevel) && bash tests/run-all.sh"}}