{"event_type": "SNAPSHOT", "timestamp": 1776984992197217000, "uuid": "cf2fae14-b0b0-40ea-8de6-f697bf3b5fe0", "env_id": "c3d2c46e-df9e-40c4-8014-5e8c9fdf3cc1", "author": "Worktree", "data": {"compiled_state": {"ticket_id": "3655-8ca5", "ticket_type": "task", "title": "Implement _ticketlib_has_flock detection and python3 fcntl fallback in ticket-lib-api.sh", "status": "closed", "author": "Test", "created_at": 1776660527618200000, "env_id": "c3d2c46e-df9e-40c4-8014-5e8c9fdf3cc1", "parent_id": "74e1-469e", "priority": 2, "assignee": "Test", "description": "## Task\n\nImplement `_ticketlib_has_flock` detection helper and fallback logic in ticket-lib-api.sh so all RED tests from task cc08-555d pass.\n\n### Changes Required\n\n1. At library source time, set detection var:\n   ```bash\n   command -v flock >/dev/null 2>&1 && _ticketlib_has_flock=1 || _ticketlib_has_flock=0\n   ```\n\n2. In any internal function that uses file locking (e.g., write_commit_event or equivalent), branch:\n   - `_ticketlib_has_flock=1`: use `flock -x -n \"$lockfile\" ...` (Linux/macOS hard requirement)\n   - `_ticketlib_has_flock=0`: use python3 fcntl.flock fallback:\n     ```python\n     import fcntl, sys, os\n     fd = open(sys.argv[1], 'w')\n     fcntl.flock(fd, fcntl.LOCK_EX)\n     # run op, then release\n     ```\n\n3. Document realpath/sha1sum/md5sum BusyBox fallbacks inline where behavior differs from GNU coreutils (flag differences in stat, sha1sum vs sha1, etc.)\n\n4. Shell-special-char safety: ensure all JSON writes use python3 json.dumps (already in ticket_reducer) — no raw bash string interpolation into JSON fields.\n\n## Testing Mode\n\nGREEN — make tests/scripts/test-ticket-platform-compat.sh pass (tests written in cc08-555d).\n\n## File Impact\n\n- plugins/dso/scripts/ticket-lib-api.sh (UPDATE — add _ticketlib_has_flock + fallback branch)\n\n## Acceptance\n\n- `bash tests/scripts/test-ticket-platform-compat.sh` exits 0 (GREEN)\n- All existing ticket tests continue to pass", "tags": [], "comments": [{"body": "WORKTREE_TRACKING:start branch=worktree-20260423-150226 session_branch=worktree-20260423-150226 timestamp=2026-04-23T22:44:35Z", "author": "Worktree", "timestamp": 1776984275657994000}, {"body": "WORKTREE_TRACKING:complete branch=worktree-20260423-150226 outcome=merged timestamp=2026-04-23T22:56:22Z", "author": "Worktree", "timestamp": 1776984982315487000}], "deps": [{"target_id": "cc08-555d", "relation": "depends_on", "link_uuid": "ee334db7-9d9c-481a-b70e-fe599783208c"}], "bridge_alerts": [], "reverts": [], "preconditions_summary": {"status": "pre-manifest"}}, "source_event_uuids": ["843fa65d-859d-4feb-a1d2-9c001d746a02", "ee334db7-9d9c-481a-b70e-fe599783208c", "a5b0c7bf-487a-48d1-91e8-599803f6da59", "459f94d6-cc33-4b74-a20f-bfa64bc873da", "73bb3f09-0cb0-458a-8db6-77c37b5efa01", "78104321-2547-484c-a7a3-71c65d1ec452"], "compacted_at": 1776984992197217000}}