{
  "dso-2bmc": {
    "deps": [],
    "priority": 1,
    "status": "open",
    "title": "Add descriptive agent name guidance to /dso:debug-everything dispatch points",
    "type": "task"
  },
  "dso-5rya": {
    "deps": [],
    "priority": 1,
    "status": "open",
    "title": "Add descriptive agent name guidance to /dso:sprint dispatch points",
    "type": "task"
  },
  "dso-6026": {
    "deps": [
      "dso-917w"
    ],
    "priority": 2,
    "status": "open",
    "title": "As a DSO practitioner, deprecated sub-agent templates have consistent anti-cover-up guidance",
    "type": "story"
  },
  "dso-6r3o": {
    "deps": [],
    "priority": 1,
    "status": "closed",
    "title": "As a developer, the CI auto-ticket-creation pattern is fully removed",
    "type": "story"
  },
  "dso-917w": {
    "deps": [],
    "priority": 1,
    "status": "open",
    "title": "As a DSO practitioner, sub-agents receive comprehensive anti-cover-up guidance in active prompt templates",
    "type": "story"
  },
  "dso-fqye": {
    "deps": [
      "dso-6r3o"
    ],
    "priority": 2,
    "status": "closed",
    "title": "Update project docs to reflect CI ticket removal",
    "type": "story"
  },
  "dso-jjli": {
    "deps": [],
    "priority": 2,
    "status": "open",
    "title": "merge-to-main.sh 'merge' phase name misleads agents into thinking code is on main",
    "type": "bug"
  },
  "dso-pcgh": {
    "deps": [],
    "priority": 1,
    "status": "open",
    "title": "Sub-agents create tickets with type 'task' instead of 'bug' when tracking discovered bugs",
    "type": "bug"
  },
  "dso-ptzz": {
    "deps": [],
    "priority": 2,
    "status": "open",
    "title": "sprint-next-batch.sh treats tk dep blockers as file conflicts, preventing non-overlapping tasks from batching",
    "type": "bug"
  },
  "dso-uu13": {
    "deps": [],
    "priority": 1,
    "status": "closed",
    "title": "Remove CI ticket creation pattern",
    "type": "epic"
  }
}
