{"event_type": "SNAPSHOT", "timestamp": 1775211469, "uuid": "5216c2bb-c763-45b2-8dfd-6ab0a6a694ee", "env_id": "c3d2c46e-df9e-40c4-8014-5e8c9fdf3cc1", "author": "Test", "data": {"compiled_state": {"ticket_id": "3a7c-e010", "ticket_type": "task", "title": "Update cross-references from MCP guide to CLI guide in all skills", "status": "closed", "author": "Test", "created_at": 1775188563, "env_id": "c3d2c46e-df9e-40c4-8014-5e8c9fdf3cc1", "parent_id": "06fa-3ba5", "priority": 2, "assignee": "Test", "description": "## Description\nUpdate all skill files and docs that reference PLAYWRIGHT-MCP-GUIDE.md to point to PLAYWRIGHT-CLI-GUIDE.md instead.\n\nFiles to check (from grep): INSTALL.md, CONFIGURATION-REFERENCE.md, playwright-debug/SKILL.md, validate-work prompts, debug-everything prompts.\n\n## File Impact\n- Multiple skill/doc files (EDIT — cross-reference updates only)\n\n## Acceptance Criteria\n- [ ] No remaining references to PLAYWRIGHT-MCP-GUIDE.md\n  Verify: ! grep -r \"PLAYWRIGHT-MCP-GUIDE\" plugins/dso/ --include=\"*.md\"\n- [ ] CLI guide referenced where MCP guide was\n  Verify: grep -r \"PLAYWRIGHT-CLI-GUIDE\" plugins/dso/ --include=\"*.md\" | head -1\n- [ ] bash tests/run-all.sh passes (exit 0)\n  Verify: bash tests/run-all.sh", "tags": [], "comments": [{"body": "CHECKPOINT 1/6: Task context loaded ✓", "author": "Test", "timestamp": 1775211310866405000}, {"body": "CHECKPOINT 2/6: Code patterns understood ✓", "author": "Test", "timestamp": 1775211341063922000}, {"body": "CHECKPOINT 3/6: Tests written (none required) ✓", "author": "Test", "timestamp": 1775211349690027000}, {"body": "CHECKPOINT 4/6: Implementation complete ✓", "author": "Test", "timestamp": 1775211368642407000}, {"body": "CHECKPOINT 5/6: Validation passed ✓", "author": "Test", "timestamp": 1775211375776972000}, {"body": "CHECKPOINT 6/6: Done ✓", "author": "Test", "timestamp": 1775211382392933000}, {"body": "Fixed: All cross-references updated from MCP to CLI guide", "author": "Test", "timestamp": 1775211468819769000}], "deps": [{"target_id": "2068-b823", "relation": "depends_on", "link_uuid": "19502ed9-4bc2-419b-8d91-f75b3414da87"}], "bridge_alerts": [], "reverts": []}, "source_event_uuids": ["f1572c4f-97f8-45da-9b41-60f5422f7e40", "19502ed9-4bc2-419b-8d91-f75b3414da87", "bec4d748-d45c-492a-bcf9-8a327fb50594", "edb0cbf2-a5e6-4092-b2aa-bf6dbd84b13e", "2a509adb-345d-4649-b2c4-d1bbbe6d9b84", "13b50ea7-4af1-413a-b038-4db19f0cc1a9", "6274cce0-328a-4913-b463-79543a95ce20", "23c56a36-ce92-4af1-9fcd-4d35ecd9b276", "8212fbb0-70b7-4b99-860d-39cbedd7713a", "378e719a-e26c-4751-b003-c0cf72681bc3", "5580738e-74d9-4351-bca8-c58cc10e49e1"], "compacted_at": 1775211469}}