{"event_type": "SNAPSHOT", "timestamp": 1776484762953603192, "uuid": "5f1fba33-d9e3-4e24-95a9-753a74116f2c", "env_id": "c3d2c46e-df9e-40c4-8014-5e8c9fdf3cc1", "author": "github-actions[bot]", "data": {"compiled_state": {"ticket_id": "82f8-c19d", "ticket_type": "task", "title": "Create tests/perf/ticket-list-timing.sh — baseline performance verification", "status": "in_progress", "author": "Test", "created_at": 1776476760213250000, "env_id": "c3d2c46e-df9e-40c4-8014-5e8c9fdf3cc1", "parent_id": "bc06-74f4", "priority": 2, "assignee": "Test", "description": "Create tests/perf/ticket-list-timing.sh. Script provisions a TICKETS_TRACKER_DIR with 500 synthetic tickets (400 with .archived marker, 100 without), times 'ticket list' (exclude_archived=true) 3 times and asserts median < 2s. Confirms the fast-skip optimization is functioning. Not a unit test — a performance regression guard. Create tests/perf/ directory if it does not exist. Add executable bit. testing_mode: RED (new behavior: perf assertion that will fail before fast-skip is implemented, pass after).", "tags": ["testing_mode:RED"], "comments": [{"body": "## Acceptance Criteria\n- [ ] Verify: tests/perf/ticket-list-timing.sh exists and is executable\n- [ ] Verify: script provisions 500 synthetic tickets (400 archived, 100 not)\n- [ ] Verify: script times 'ticket list' 3 times and asserts median < 2s\n- [ ] Verify: tests/perf/ directory created if missing", "author": "Test", "timestamp": 1776477785234229000}, {"body": "CHECKPOINT 1/6: Task context loaded ✓", "author": "Test", "timestamp": 1776477980011819000}, {"body": "CHECKPOINT 2/6: Code patterns understood ✓ — reviewed make_v3_ticket pattern, ticket-lifecycle.sh ARCHIVED event structure, .archived marker file convention, and TICKETS_TRACKER_DIR injection pattern", "author": "Test", "timestamp": 1776478131029470000}, {"body": "CHECKPOINT 3/6: Tests written ✓ — tests/perf/ticket-list-timing.sh created", "author": "Test", "timestamp": 1776478145079358000}, {"body": "CHECKPOINT 4/6: Implementation complete ✓ — script runs, provisions 500 tickets (400 archived, 100 active), times 3 runs, asserts median < 2s. Currently PASS (0.419s median) — optimization already provides fast behavior. Script will catch regressions if optimization is removed.", "author": "Test", "timestamp": 1776478179217078000}, {"body": "CHECKPOINT 5/6: Validation passed ✓ — executable bit set (-rwxr-xr-x), bash -n syntax check clean, script runs end-to-end successfully", "author": "Test", "timestamp": 1776478202799362000}, {"body": "CHECKPOINT 6/6: Done ✓ — All acceptance criteria met. AC1: file exists at tests/perf/ticket-list-timing.sh, executable. AC2: provisions 500 tickets (400 archived with ARCHIVED event + .archived marker, 100 active). AC3: times 3 runs, asserts median < threshold (default 2s). AC4: tests/perf/ directory created. Median on this machine: ~0.42s.", "author": "Test", "timestamp": 1776478218251731000}], "deps": [{"target_id": "9eff-53b7", "relation": "blocked_by", "link_uuid": "216bde3d-5b9c-4e59-b6db-e9b9404e88fd"}, {"target_id": "dfa2-c834", "relation": "blocked_by", "link_uuid": "3fceb1da-bce2-4b07-83a3-68ed8be72222"}, {"target_id": "800d-293c", "relation": "blocked_by", "link_uuid": "510b3fb1-5245-4d12-90a7-23e70056d642"}, {"target_id": "0b1b-fb00", "relation": "blocked_by", "link_uuid": "fb1557bd-8f05-42d8-b90a-695e5a36b952"}], "bridge_alerts": [], "reverts": []}, "source_event_uuids": ["56b84881-c89f-4bcd-b292-ac1e6e0e3f97", "216bde3d-5b9c-4e59-b6db-e9b9404e88fd", "3fceb1da-bce2-4b07-83a3-68ed8be72222", "510b3fb1-5245-4d12-90a7-23e70056d642", "fb1557bd-8f05-42d8-b90a-695e5a36b952", "93bb6faf-7826-43b0-ba06-c1eeeceab9c6", "96111f76-2753-45e9-ab85-fb2c0820c372", "fd1fb254-b8d5-4c2e-89c2-b22ffd98ee56", "877798c3-775e-4562-8f4c-105adef119e1", "f816ae67-6dee-483d-857a-72d3d48f2149", "56ea4473-bd43-4222-9517-a7797a2a549e", "647e3527-9956-4823-b62c-4dabbc5280f4", "e67d2069-9452-4466-bf3a-9a9ef1c6c0d0"], "compacted_at": 1776484762953603192}}