{"timestamp": 1774683624358626000, "uuid": "c99f5b7d-7cbe-4919-ba46-8e3dd366cd86", "event_type": "COMMENT", "env_id": "c3d2c46e-df9e-40c4-8014-5e8c9fdf3cc1", "author": "Joe Oakhart", "data": {"body": "CHECKPOINT 4/6: Implementation complete \u2713 \u2014 (a) ticket-edit.sh: added 'tags' to ALLOWED_FIELDS and updated usage string to include --tags=VALUE; (b) ticket-reducer.py: added 'tags': [] to initial state dict, added tags-specific EDIT handling that splits comma-separated string into list; (c) ticket-show.sh: no changes needed \u2014 it already outputs raw reducer JSON which naturally includes all state fields including tags."}}