{"timestamp": 1776285698, "uuid": "24173687-5e32-4752-935a-ac5e59a76154", "event_type": "CREATE", "env_id": "c3d2c46e-df9e-40c4-8014-5e8c9fdf3cc1", "author": "Test", "data": {"ticket_type": "bug", "title": "dso-setup.sh: erroneous auto-install block in detect_prerequisites causes CI failures (d10654da)", "parent_id": "", "description": "Commit d10654da added an auto-install block inside detect_prerequisites() that runs 'brew install / apt-get install' unconditionally before prerequisite checks. This broke test_prereq_missing_precommit_warning and test_prereq_missing_python3_warning in CI on ubuntu-24.04 (typo 'pyrhon', wrong function, blocking behavior). Fix: remove the block from detect_prerequisites() entirely \u2014 this function should detect, not install.", "tags": [], "priority": 2, "assignee": "Test"}}