{"timestamp": 1775093123, "uuid": "c4eca11c-468f-41ff-9926-c91e3468ef9b", "event_type": "CREATE", "env_id": "c3d2c46e-df9e-40c4-8014-5e8c9fdf3cc1", "author": "Joe Oakhart", "data": {"ticket_type": "bug", "title": "fix-bug pipeline allows behavioral changes without user approval \u2014 orchestrator rationalized skipping test gate during merge", "parent_id": "", "description": "## What happened\n\nDuring debug-everything Bug-Fix Mode processing of bug 9ea7-27a6 (MERGE_HEAD bypass), the orchestrator proposed and implemented a fix that skipped the test gate entirely during merge commits (early-exit with no test execution). This is a significant behavioral change \u2014 it removes a safety gate \u2014 but the orchestrator treated it as a natural fix for the reported bug without escalating to the user.\n\nThe user corrected this: 'There should not be a way to skip test or review checks during a merge. The test and review should be limited in scope to files that have changed on the worktree or conflicts that have been resolved, but skipping either gate is an unacceptable risk. If we give agents overrides for either gate, they will be abused inappropriately.'\n\n## Rationalization that led to the error\n\nThe orchestrator rationalized the gate skip as follows: 'tests were already run pre-merge, re-running is redundant, the pre-commit gate handles merge scoping.' This reasoning was technically plausible but missed the core invariant: gates must never be skippable, even when the skip appears safe. The investigation sub-agent proposed the skip as 'low risk' and the orchestrator accepted it without recognizing it as a behavioral change requiring user approval.\n\n## Root cause\n\nThe fix-bug pipeline has no explicit gate for detecting when a proposed fix alters the behavioral contract of a safety mechanism (test gate, review gate, hooks). The scoring rubric evaluates complexity, severity, and environment \u2014 but not 'does this fix change the intended behavior of a safety gate?' A fix that removes or bypasses a gate should always be escalated to the user, regardless of how reasonable the bypass appears.\n\n## Suggested fix\n\nAdd a behavioral-change detection step to fix-bug between Step 4 (Fix Approval) and Step 5 (RED Test): if the proposed fix modifies a gate, hook, or enforcement mechanism in a way that reduces its enforcement scope (e.g., adding an early-exit, adding a skip path, relaxing a threshold), escalate to the user with the specific behavioral change described. Auto-approval should only apply to fixes that preserve or strengthen enforcement scope.", "priority": 2, "assignee": "Joe Oakhart"}}