{"timestamp": 1774806412513106000, "uuid": "ac17fc1d-7d3a-4d86-bd0c-8f066e68b10e", "event_type": "COMMENT", "env_id": "c3d2c46e-df9e-40c4-8014-5e8c9fdf3cc1", "author": "Joe Oakhart", "data": {"body": "AC amendment (review): test_modifier_enriches_dialog (case 8) should assert dialog_context includes the modifier's 'evidence' field value \u2014 NOT 'annotation'. Use 'evidence' consistently per gate-signal-schema.md contract. Also add test_malformed_json_input: pipe invalid JSON -> route:auto-fix (fail-open, not crash)."}}