{"author":"Test","data":{"assignee":"Test","description":"## Incident Overview\n\nSame root cause as 999e-cf69 but across 15 test files. Under set -uo pipefail, echo \"$large_var\" | grep -qE exits with SIGPIPE (141) when grep -q exits early after finding a match. Pipefail reports pipeline failure, making if conditions false even though grep matched.\n\n50 instances found across: test-implementation-plan-task-description.sh (currently failing), test-fix-bug-intent-conflict-handling.sh, test-merge-to-main-resume-cwd.sh, test-merge-to-main.sh, test-harvest-worktree.sh, test-ui-designer-agent.sh, test-ticket-lib-api.sh, test-merge-to-main-cleanliness.sh, test-check-contract-schemas.sh, and others.\n\nFix: replace echo \"$var\" | grep -q with grep -q <<< \"$var\" (here-string, avoids pipe) or grep -q \"$FILE\" directly (when file path available).","parent_id":"","priority":2,"tags":[],"ticket_type":"bug","title":"[tests]: echo|grep-q+pipefail SIGPIPE -> systematic false-negatives across 15 test files in CI"},"env_id":"c3d2c46e-df9e-40c4-8014-5e8c9fdf3cc1","event_type":"CREATE","timestamp":1777131189333209000,"uuid":"077e48ab-1e48-46fd-b5b5-98804c31ad70"}
