{"event_type": "SNAPSHOT", "timestamp": 1776455692351397000, "uuid": "ef006c82-5861-478c-b524-41e41e239347", "env_id": "c3d2c46e-df9e-40c4-8014-5e8c9fdf3cc1", "author": "Test", "data": {"compiled_state": {"ticket_id": "dso-gq8v", "ticket_type": "task", "title": "Implement cutover rollback logic: detect committed vs uncommitted failure and revert", "status": "closed", "author": null, "created_at": 1774225447, "env_id": null, "parent_id": "w21-2a9w", "priority": 1, "assignee": "Joe Oakhart", "description": "", "tags": [], "comments": [], "deps": [{"target_id": "dso-pjcl", "relation": "depends_on", "link_uuid": "a5db41e0-9703-4794-898b-b2522c3e5b9d"}], "bridge_alerts": [], "reverts": [], "archived": true}, "source_event_uuids": ["e2f04701-19cb-4d7e-9e4f-6332288b8198", "b585ce12-1a3d-4bf9-ab53-50f0d76a3a3a", "a5db41e0-9703-4794-898b-b2522c3e5b9d", "99842e15-56e0-4e63-a37f-dd18e15ba849"], "compacted_at": 1776455692351397000}}