{"timestamp": 1774805171, "uuid": "c51e52b3-ff32-4895-9df8-fe15468f411f", "event_type": "CREATE", "env_id": "c3d2c46e-df9e-40c4-8014-5e8c9fdf3cc1", "author": "Joe Oakhart", "data": {"ticket_type": "task", "title": "RED test: escalation routing integration in fix-bug SKILL.md", "parent_id": "a2f0-9641", "description": "Create tests/skills/test_fix_bug_escalation_routing.py with structural validation tests.\n\nTests:\n1. test_routing_section_exists \u2014 SKILL.md contains escalation routing section\n2. test_routing_dispatches_script \u2014 references gate-escalation-router.py\n3. test_auto_fix_path \u2014 documents 0-signal auto-fix path\n4. test_dialog_path \u2014 documents 1-signal dialog with blast radius context\n5. test_escalate_path \u2014 documents 2+-signal escalation to /dso:brainstorm\n6. test_complex_override \u2014 documents COMPLEX always-escalate\n7. test_routing_after_gates \u2014 routing appears after all gate sections\n8. test_interactivity_integration \u2014 documents debug-everything interactivity flag integration\n\nDocstring: structural metadata validation \u2014 design contract verification.\nAppend to .test-index for fix-bug/SKILL.md (comma-separated value list).\n\n## Acceptance Criteria\n- [ ] Test file exists\n  Verify: test -f tests/skills/test_fix_bug_escalation_routing.py\n- [ ] At least 8 test functions\n  Verify: grep -c 'def test_' tests/skills/test_fix_bug_escalation_routing.py | awk '{exit ($1 < 8)}'\n- [ ] .test-index updated\n  Verify: grep 'fix-bug/SKILL.md' $(git rev-parse --show-toplevel)/.test-index | grep -q 'test_fix_bug_escalation_routing'", "priority": 1, "assignee": "Joe Oakhart"}}