{"event_type": "CREATE", "env_id": "", "jira_key": "NAK-1", "local_id": "jira-nak-1", "timestamp": 1774319047, "run_id": "23469985247", "data": {"jira_key": "NAK-1", "fields": {"assignee": null, "issuetype": {"avatarId": 10318, "description": "A small, distinct piece of work.", "entityId": "a9308e45-b69a-426e-9bb1-ae52aa691798", "hierarchyLevel": 0, "iconUrl": "https://jira-prod-us-51-as-2.prod.atl-paas.net/rest/api/2/universal_avatar/view/type/issuetype/avatar/10318?size=medium", "id": "17324", "name": "Task", "self": "https://jira-prod-us-51-as-2.prod.atl-paas.net/rest/api/3/issuetype/17324", "subtask": false}, "priority": {"iconUrl": "https://jira-prod-us-51-as-2.prod.atl-paas.net/images/icons/priorities/medium_new.svg", "id": "3", "name": "Medium", "self": "https://jira-prod-us-51-as-2.prod.atl-paas.net/rest/api/3/priority/3"}, "status": {"description": "", "iconUrl": "https://jira-prod-us-51-as-2.prod.atl-paas.net/", "id": "21389", "name": "Open", "self": "https://jira-prod-us-51-as-2.prod.atl-paas.net/rest/api/3/status/21389", "statusCategory": {"colorName": "blue-gray", "id": 2, "key": "new", "name": "To Do", "self": "https://jira-prod-us-51-as-2.prod.atl-paas.net/rest/api/3/statuscategory/2"}}, "summary": "Orals & Tech Issues Mini Project"}}}