{"event_type": "SNAPSHOT", "timestamp": 1774560425, "uuid": "158be3b8-cee6-4a3c-9d97-3e01676596d4", "env_id": "c3d2c46e-df9e-40c4-8014-5e8c9fdf3cc1", "author": "github-actions[bot]", "data": {"compiled_state": {"ticket_id": "02fa-fa23", "ticket_type": "task", "title": "RED: Write behavioral tests for jira-credential-helper.sh", "status": "closed", "author": "Joe Oakhart", "created_at": 1774492410, "env_id": "c3d2c46e-df9e-40c4-8014-5e8c9fdf3cc1", "parent_id": "00ff-c1af", "priority": 2, "assignee": "Joe Oakhart", "comments": [{"body": "## TDD: This IS the RED test task\n\nCreate tests/scripts/test-jira-credential-helper.sh\n\n## Tests\n1. test_detect_all_vars_set: Set JIRA_URL/USER/TOKEN in env, call helper, assert DETECTED contains all 3\n2. test_detect_partial_vars: Set only JIRA_URL, assert DETECTED=JIRA_URL and MISSING includes JIRA_USER,JIRA_API_TOKEN\n3. test_missing_vars_show_guidance: Unset all, assert output includes description text and API token URL\n4. test_token_confirm_signal: Set JIRA_API_TOKEN, assert CONFIRM_BEFORE_COPY marker in output\n5. test_jira_project_output: Call with --project=DIG, assert JIRA_PROJECT=DIG\n6. test_no_env_vars: Clean env, assert all-missing output\n\n## .test-index\nAdd: plugins/dso/scripts/jira-credential-helper.sh: tests/scripts/test-jira-credential-helper.sh [test_detect_all_vars_set]\n\n## Integration test exemption: gh API unavailable in CI. Documented in test header.\n\n## Acceptance Criteria\n- [ ] bash tests/run-all.sh passes\n  Verify: cd $(git rev-parse --show-toplevel) && bash tests/run-all.sh\n- [ ] Test file exists\n  Verify: test -f $(git rev-parse --show-toplevel)/tests/scripts/test-jira-credential-helper.sh\n- [ ] At least 6 test functions\n  Verify: grep -c 'test_' $(git rev-parse --show-toplevel)/tests/scripts/test-jira-credential-helper.sh | awk '{exit ($1 < 6)}'\n- [ ] .test-index entry with RED marker\n  Verify: grep -q 'jira-credential-helper.sh' $(git rev-parse --show-toplevel)/.test-index", "author": "Joe Oakhart", "timestamp": 1774492447620418000}, {"body": "CHECKPOINT 1/6: Task context loaded ✓", "author": "Joe Oakhart", "timestamp": 1774492715039191000}, {"body": "CHECKPOINT 2/6: Code patterns understood ✓", "author": "Joe Oakhart", "timestamp": 1774492744120319000}, {"body": "CHECKPOINT 3/6: Tests written ✓", "author": "Joe Oakhart", "timestamp": 1774492800470962000}, {"body": "CHECKPOINT 4/6: Implementation complete (RED test — no impl needed) ✓", "author": "Joe Oakhart", "timestamp": 1774492805140839000}, {"body": "CHECKPOINT 5/6: Validation passed ✓", "author": "Joe Oakhart", "timestamp": 1774492816686998000}, {"body": "CHECKPOINT 6/6: Done ✓", "author": "Joe Oakhart", "timestamp": 1774492828057960000}, {"body": "CHECKPOINT 6/6: Done ✓ — Files created/modified per agent report. Tests: pass.", "author": "Joe Oakhart", "timestamp": 1774493130681769000}, {"body": "Fixed: Batch 1 committed and pushed (818b0c49)", "author": "Joe Oakhart", "timestamp": 1774493499169930000}], "deps": [], "bridge_alerts": [], "reverts": [], "description": ""}, "source_event_uuids": ["19381f8a-e89b-45f7-a862-be2c408c4262", "af594bcb-432d-445e-933e-6e1396875f9f", "8cbe537c-1626-44f0-b690-9370ebed0b95", "3a0d3b30-7591-49d0-b828-ff1d6f58bc8d", "a64a67ee-fa66-44d4-a52a-99dcdef0272b", "6c0030a7-236f-4724-9520-eedcfa3d8e10", "4c82c864-2f58-451c-b757-e761eaee6397", "774be6e4-c45c-45cd-9086-a0383ef8f10d", "c4412695-318a-4896-8c67-93ef03679dad", "b9ec0240-9c7e-4fb7-8991-0a4733ab837c", "98523b0d-b098-4575-8828-18a5b2a6e71a", "582901fe-a4e8-4146-b54a-891d1e9c2b85", "1774500213-f23acc93-b036-4bf6-9fe5-eabece9ae888-SYNC.json"], "compacted_at": 1774560425}}