{"timestamp": 1774680872231199000, "uuid": "2df3ac6e-a273-49eb-b375-1cb5fdaa18ef", "event_type": "COMMENT", "env_id": "c3d2c46e-df9e-40c4-8014-5e8c9fdf3cc1", "author": "Joe Oakhart", "data": {"body": "CHECKPOINT 4/6: Implementation complete \u2713 \u2014 Updated brainstorm Phase 3 Step 1 (epic create+comment \u2192 create -d), roadmap Phase 5 Step 2 (epic create+comment \u2192 create -d), preplanning new_story action (create+comment \u2192 create -d) and story creation (create+comment \u2192 create -d), implementation-plan task creation (create+comment \u2192 create -d), impl-plan-dispatch.md permitted flags (--acceptance \u2192 -d/--description), design-wireframe enhancement story (fixed broken -d: moved ticket_type to correct position)"}}