{"timestamp": 1776567594412537000, "uuid": "e5d12587-0162-4855-953d-d2ea1ab1bde6", "event_type": "CREATE", "env_id": "c3d2c46e-df9e-40c4-8014-5e8c9fdf3cc1", "author": "Test", "data": {"ticket_type": "bug", "title": "Parser: valid JSON input -> Unexpected token (exit 1)", "parent_id": "", "description": "### 2. Incident Overview\n\n* **Scenario Type:** Sub-Agent Blocker\n\n#### Expected Behavior\n\nThe system should process input without errors when given valid JSON.\n\n#### Actual Behavior\n\nThe system exits with code 1 and prints 'Unexpected token' to stderr.", "tags": [], "priority": 2, "assignee": "Test"}}