{"timestamp": 1774668354981379000, "uuid": "e58d76b5-ba77-4347-af1f-3bb87def3227", "event_type": "COMMENT", "env_id": "c3d2c46e-df9e-40c4-8014-5e8c9fdf3cc1", "author": "Joe Oakhart", "data": {"body": "## Description\n\n**What**: Refactor ticket-graph.py to use a single reduce_all_tickets call shared across _find_direct_blockers, _compute_dep_graph children scan, and _get_ticket_status:\n(a) Add reduce_all_tickets call at the top of build_dep_graph (or _compute_dep_graph) that loads all non-archived tickets once\n(b) Pass the pre-loaded ticket_states dict to _find_direct_blockers and _compute_dep_graph\n(c) Replace per-ticket _reduce_ticket calls in Source 2 scan and children scan with lookups into pre-loaded dict\n(d) _get_all_blocked_by remains unchanged (archived mid-chain traversal must work)\n(e) Preserve compute_archive_eligible's exclude_archived=False\n(f) Remove .test-index RED marker\n\n### Files to modify\n- plugins/dso/scripts/ticket-graph.py\n- .test-index (remove RED marker)\n\n## Acceptance Criteria\n- [ ] bash tests/run-all.sh passes\n  Verify: bash tests/run-all.sh\n- [ ] ruff check passes\n  Verify: ruff check plugins/dso/scripts/ticket-graph.py\n- [ ] .test-index RED marker removed\n  Verify: ! grep -q 'ticket-graph.py.*\\[test_build_dep_graph_single_batch_scan' .test-index"}}