{"event_type": "SNAPSHOT", "timestamp": 1776490406407169000, "uuid": "cacaf9dc-dca2-45dc-998a-816b56061ee6", "env_id": "c3d2c46e-df9e-40c4-8014-5e8c9fdf3cc1", "author": "Test", "data": {"compiled_state": {"ticket_id": "9ec3-bdb7", "ticket_type": "task", "title": "Implement marker-presence in compute_dir_hash() in ticket_reducer/_cache.py", "status": "closed", "author": "Test", "created_at": 1776476928588947000, "env_id": "c3d2c46e-df9e-40c4-8014-5e8c9fdf3cc1", "parent_id": "bc06-74f4", "priority": 2, "assignee": "Test", "description": "Update plugins/dso/scripts/ticket_reducer/_cache.py compute_dir_hash() (line 38) to include .archived marker presence in the hash. After hashing event files, check os.path.exists(os.path.join(ticket_dir, '.archived')) and append 'marker:present' or 'marker:absent' to hash_parts. This ensures cache invalidation when a marker is added or removed without any event file changes. Covers SC5. testing_mode: GREEN (T12 covers behavior).", "tags": ["testing_mode:GREEN"], "comments": [{"body": "## Acceptance Criteria\n- [ ] Verify: compute_dir_hash() includes marker presence in hash_parts\n- [ ] Verify: 'marker:present' appended when .archived exists in ticket_dir\n- [ ] Verify: 'marker:absent' appended when .archived does not exist\n- [ ] Verify: cache invalidates correctly when marker state changes", "author": "Test", "timestamp": 1776477787533494000}, {"body": "CHECKPOINT 1/6: Task context loaded ✓", "author": "Test", "timestamp": 1776477996334546000}, {"body": "CHECKPOINT 2/6: Code patterns understood ✓ — compute_dir_hash() at line 38, builds hash_parts from event filenames+sizes, then SHA256. Need to append marker:present/absent after the loop.", "author": "Test", "timestamp": 1776478003104216000}, {"body": "CHECKPOINT 3/6: Tests written (none required — GREEN mode) ✓", "author": "Test", "timestamp": 1776478012392519000}, {"body": "CHECKPOINT 4/6: Implementation complete ✓ — appended marker:present/marker:absent to hash_parts after event file loop in compute_dir_hash()", "author": "Test", "timestamp": 1776478026167378000}, {"body": "CHECKPOINT 5/6: Validation passed ✓ — ruff: all checks passed; pytest -k cache: 8/8 passed", "author": "Test", "timestamp": 1776478103298175000}, {"body": "CHECKPOINT 6/6: Done ✓ — All 4 AC verified. compute_dir_hash() now appends marker:present/marker:absent after event file loop, ensuring cache invalidation when .archived marker is added/removed.", "author": "Test", "timestamp": 1776478120333153000}], "deps": [{"target_id": "71ee-f1de", "relation": "blocked_by", "link_uuid": "4b200ebc-4378-4bf6-93f5-ef60fe05a42c"}], "bridge_alerts": [], "reverts": []}, "source_event_uuids": ["465a4e99-f4bc-49a3-9e1a-2d01e3c1c7b8", "4b200ebc-4378-4bf6-93f5-ef60fe05a42c", "e5537fa4-fcc2-4057-beba-427d2546f90b", "e3495013-bdb5-41cc-84b9-ca30e48fb591", "0add7402-fd89-40f6-843d-e356b7c0eea1", "13c127a8-f6fd-45ff-a2ef-f845890ec4af", "6f4ffbfc-1fe5-4135-96d0-00a91037e7e6", "66bea538-bba4-43b5-86a0-1fafa1ec0a59", "222c0e89-0a30-4f8b-a2b2-a1a8e0a17007", "fdf6c88b-2dc3-4824-8fb5-fe1fc1758df9", "feeea3c6-f8ee-436c-b1ad-238c79beb4d0"], "compacted_at": 1776490406407169000}}