{"timestamp": 1775510581, "uuid": "4f49e92c-15db-459f-b3e4-1d82395649f0", "event_type": "CREATE", "env_id": "c3d2c46e-df9e-40c4-8014-5e8c9fdf3cc1", "author": "Test", "data": {"ticket_type": "task", "title": "Update sprint RED Task Dispatch and red-task-escalation.md for TEST_RESULT:no_new_tests_needed", "parent_id": "80c9-df3c", "description": "## Description\n\nUpdate the sprint orchestrator and shared escalation template to handle the new TEST_RESULT:no_new_tests_needed value.\n\n### Steps\n1. In `plugins/dso/skills/sprint/SKILL.md` Phase 4 RED Task Dispatch section, add a new case to the TEST_RESULT parser table:\n   - `TEST_RESULT:no_new_tests_needed` \u2192 Success. No new test was needed. Do NOT escalate to Tier 2. Proceed to normal task execution without TDD setup.\n2. In `plugins/dso/skills/sprint/prompts/red-task-escalation.md`, update the Tier 1 parser table:\n   - Add row: `TEST_RESULT:no_new_tests_needed` \u2192 Success. No TDD setup needed. Do NOT escalate.\n   - Update the Tier 3 parser table with the same addition\n   - Update the flow diagram to show the third outcome path\n\n### File Impact\n- `plugins/dso/skills/sprint/SKILL.md` \u2014 Edit (RED Task Dispatch section)\n- `plugins/dso/skills/sprint/prompts/red-task-escalation.md` \u2014 Edit (parser tables + flow diagram)\n\n## Testing Mode\nUPDATE\n\n## Acceptance Criteria\n- [ ] `bash tests/run-all.sh` passes (exit 0)\n  Verify: bash tests/run-all.sh\n- [ ] Sprint SKILL.md handles no_new_tests_needed\n  Verify: grep -q \"no_new_tests_needed\" plugins/dso/skills/sprint/SKILL.md\n- [ ] Escalation template handles no_new_tests_needed\n  Verify: grep -q \"no_new_tests_needed\" plugins/dso/skills/sprint/prompts/red-task-escalation.md", "tags": [], "priority": 2, "assignee": "Test"}}