{"event_type": "SNAPSHOT", "timestamp": 1775696669, "uuid": "66a1552a-c8fb-4f52-9256-6583976acd05", "env_id": "c3d2c46e-df9e-40c4-8014-5e8c9fdf3cc1", "author": "Test", "data": {"compiled_state": {"ticket_id": "79ac-5886", "ticket_type": "bug", "title": "Sprint orchestrator: /end-session not invoked at sprint Phase 9 completion — user must trigger it manually", "status": "closed", "author": "Test", "created_at": 1775694609, "env_id": "c3d2c46e-df9e-40c4-8014-5e8c9fdf3cc1", "parent_id": null, "priority": 2, "assignee": "Test", "description": "## Incident Overview\nAfter /dso:sprint completed all stories, closed the epic, and returned control, the orchestrator did not invoke /dso:end-session. The user had to issue the /end-session command explicitly.\n\n## Root Cause\nThe sprint orchestrator rationalized not running /end-session at Phase 9 (session wrap-up) because the skill instruction files being worked on included end-session guidance and the orchestrator conflated 'following the skill' with 'the skill has already run.' It also may have treated /end-session as optional or as a user-initiated step rather than a mandatory sprint-completion step.\n\n## Expected Behavior\n/dso:sprint Phase 9 (or final phase) must invoke /dso:end-session automatically after the epic is closed and the session summary is ready. The user should not need to issue it manually.\n\n## Impact\n- Worktree may not be merged to main\n- Ticket sync may not run\n- Worktree cleanup may be skipped\n- Technical learnings are not extracted\n- Session is left in an ambiguous state\n\n## Fix\nVerify that sprint's final phase explicitly calls /dso:end-session (via the Skill tool) after all stories are closed and the epic is verified complete. This should not be optional and should not require user intervention.", "tags": ["CLI_user"], "comments": [], "deps": [], "bridge_alerts": [], "reverts": []}, "source_event_uuids": ["0c668889-1dfa-4603-9df0-360267bc4e8e", "89974c47-49b7-4029-a34c-488b8916e2c7"], "compacted_at": 1775696669}}