{"event_type": "SNAPSHOT", "timestamp": 1777182806494521000, "uuid": "9a8e8fe8-2b7e-4939-8239-2c9b4fdaf098", "env_id": "c3d2c46e-df9e-40c4-8014-5e8c9fdf3cc1", "author": "Test", "data": {"compiled_state": {"ticket_id": "a190-d780", "ticket_type": "bug", "title": "[CONFIGURATION-REFERENCE.md]: commands.test_dirs missing -> CI test-config-keys-documented.sh fails", "status": "closed", "author": "Test", "created_at": 1777182577258979000, "env_id": "c3d2c46e-df9e-40c4-8014-5e8c9fdf3cc1", "parent_id": null, "priority": 2, "assignee": "Test", "description": "## Incident Overview\n\nCI workflow run 24946719518 fails at test-config-keys-documented.sh:\n  FAIL: all config keys are documented in CONFIGURATION-REFERENCE.md (zero gap lines)\n  undocumented keys found: commands.test_dirs\n\n## Source\nplugins/dso/scripts/validate.sh:133 reads `commands.test_dirs` (colon-separated list of test directories used by test-batched.sh resumable bash runner). The key has no entry in plugins/dso/docs/CONFIGURATION-REFERENCE.md.\n\n## Fix\nAdd entry for `commands.test_dirs` documenting purpose, format, and default behavior. This is the root cause of the latest main CI failure and blocks scripts/release.sh.", "tags": [], "comments": [{"body": "Classification: mechanical (config syntax / docs gap; deterministic fix). Mechanical Fix Path.", "author": "Test", "timestamp": 1777182582108019000}], "deps": [], "bridge_alerts": [], "reverts": [], "preconditions_summary": {"status": "pre-manifest"}}, "source_event_uuids": ["c95076c5-04a9-4fe4-889b-f09ae2b58ca1", "51d81545-6252-430d-bdf4-dc7bb455bc5a", "d1ddef1e-9b2a-4554-8bf3-6d31ca86226b", "f472048b-fe85-4d81-86fa-f24e8da4e52c"], "compacted_at": 1777182806494521000}}