{"event_type": "SNAPSHOT", "timestamp": 1776455690853876000, "uuid": "1f2ba68b-e15f-4610-8bb2-d45c672f3ab4", "env_id": "c3d2c46e-df9e-40c4-8014-5e8c9fdf3cc1", "author": "Test", "data": {"compiled_state": {"ticket_id": "dso-cnj5", "ticket_type": "task", "title": "Register ticket gate in pre-commit-config.example.yaml, dso-setup.sh, and project-setup skill", "status": "closed", "author": null, "created_at": 1774297652, "env_id": null, "parent_id": "dso-78iq", "priority": 1, "assignee": "Joe Oakhart", "description": "", "tags": [], "comments": [], "deps": [{"target_id": "dso-vl19", "relation": "depends_on", "link_uuid": "c0eff4c0-4ca4-4ce7-9c4e-f34e1a3f82bc"}], "bridge_alerts": [], "reverts": [], "archived": true}, "source_event_uuids": ["a44bc253-00ab-435d-b9af-6f5e7366e2a1", "bc0e97cc-2ec6-4cfc-b8f3-b46478ef3bb7", "c0eff4c0-4ca4-4ce7-9c4e-f34e1a3f82bc", "e030fe2d-d8e0-4ac8-971a-f26023e3178a"], "compacted_at": 1776455690853876000}}