{"timestamp": 1775959779, "uuid": "cbee890e-57c0-4065-9d0e-67a0572959ce", "event_type": "CREATE", "env_id": "c3d2c46e-df9e-40c4-8014-5e8c9fdf3cc1", "author": "Test", "data": {"ticket_type": "task", "title": "30c0-6d16: Task B \u2014 Add INTENT_CONFLICT handling to fix-bug Step 1.5 and update Step 1.7", "parent_id": "", "description": "## Story\n30c0-6d16 \u2014 fix-bug Gate 1a pauses investigation when intent-search detects conflicting caller usage\n\n## testing_mode\nUPDATE\n\n## TDD (GREEN phase \u2014 makes Task A tests pass)\nModify plugins/dso/skills/fix-bug/SKILL.md Step 1.5 to add INTENT_CONFLICT as 4th terminal outcome and update Step 1.7 to include intent-conflict in the skip condition. All 5 tests in test-fix-bug-intent-conflict-handling.sh turn GREEN after this task.\n\n## File to Modify\nplugins/dso/skills/fix-bug/SKILL.md\n\n## Required Changes\n\n### Step 1.5: Add INTENT_CONFLICT as 4th terminal outcome\n\nIn the outcomes section of Step 1.5 (Gate 1a outcomes), after the 'ambiguous' outcome bullet, add:\n\n**4th outcome \u2014 intent-conflict** (triggered: true, additional fields: behavioral_claim, conflicting_callers, dependency_classification)\n\nWhen intent-search emits INTENT_CONFLICT (triggered=true with behavioral_claim and conflicting_callers fields), investigation PAUSES. Set GATE_1A_RESULT='intent-conflict'.\n\nPresent the user with:\n- The behavioral_claim from the agent (what the ticket says should happen)\n- The conflicting_callers list (callers that depend on the current behavior)\n- The dependency_classification (behavioral_dependency or incidental_usage)\n- Three resolution options:\n  1. **Confirm ticket correct** \u2014 proceed to Step 2 investigation with the ticket as-is\n  2. **Confirm current behavior correct** \u2014 close the ticket (behavior is intentional; callers depend on it)\n  3. **Revise ticket description** \u2014 allow user to update the ticket text, then re-run Gate 1a\n\nNon-interactive mode handling:\n- When FIX_BUG_INTERACTIVE=false: defer as INTERACTIVITY_DEFERRED ticket comment; proceed to Step 2 with the ticket's stated behavior as safe default (do not block investigation)\n\nThis outcome is TERMINAL \u2014 like intent-contradicting, it skips Gate 1b.\n\n### Step 1.7: Update Gate 1b conditional\n\nIn the Step 1.7 section, update the 'When to run' condition to handle the 4th case:\n- BEFORE: 'Only when GATE_1A_RESULT=ambiguous. Skip to Step 2 immediately if GATE_1A_RESULT is intent-aligned or intent-contradicting.'\n- AFTER: 'Only when GATE_1A_RESULT=ambiguous. Skip to Step 2 immediately if GATE_1A_RESULT is intent-aligned, intent-contradicting, OR intent-conflict.'\n\n## .test-index Update (REQUIRED)\nRemove RED marker [test_intent_conflict_outcome_exists]:\n- BEFORE: plugins/dso/skills/fix-bug/SKILL.md: tests/scripts/test-fix-bug-intent-conflict-handling.sh [test_intent_conflict_outcome_exists]\n- AFTER: plugins/dso/skills/fix-bug/SKILL.md: tests/scripts/test-fix-bug-intent-conflict-handling.sh\n\n## Acceptance Criteria\n- [ ] 'intent-conflict' outcome documented in fix-bug/SKILL.md Step 1.5\n  Verify: grep -q 'intent-conflict' plugins/dso/skills/fix-bug/SKILL.md\n- [ ] Three resolution options documented near INTENT_CONFLICT handling\n  Verify: grep -q 'confirm ticket correct\\|confirm current behavior\\|revise ticket description' plugins/dso/skills/fix-bug/SKILL.md\n- [ ] GATE_1A_RESULT assigned intent-conflict\n  Verify: grep -q \"GATE_1A_RESULT.*intent-conflict\\|intent-conflict.*GATE_1A_RESULT\" plugins/dso/skills/fix-bug/SKILL.md\n- [ ] Step 1.7 updated to skip Gate 1b for intent-conflict\n  Verify: grep -A5 'Step 1.7\\|Gate 1b' plugins/dso/skills/fix-bug/SKILL.md | grep -q 'intent-conflict'\n- [ ] Non-interactive INTERACTIVITY_DEFERRED handling for intent-conflict\n  Verify: grep -B2 -A2 'INTERACTIVITY_DEFERRED' plugins/dso/skills/fix-bug/SKILL.md | grep -q 'intent-conflict'\n- [ ] RED marker removed from .test-index\n  Verify: grep 'test-fix-bug-intent-conflict-handling.sh' $(git rev-parse --show-toplevel)/.test-index && ! grep 'test-fix-bug-intent-conflict-handling.sh.*\\[test_intent_conflict_outcome_exists\\]' $(git rev-parse --show-toplevel)/.test-index\n- [ ] All 5 tests in test-fix-bug-intent-conflict-handling.sh pass\n  Verify: bash tests/scripts/test-fix-bug-intent-conflict-handling.sh 2>&1 | grep -c 'PASS:' | awk '{exit ($1 < 5)}'\n- [ ] plugins/dso/scripts/validate.sh --ci passes\n  Verify: plugins/dso/scripts/validate.sh --ci", "tags": [], "priority": 2, "assignee": "Test"}}