{"timestamp": 1775857172544161000, "uuid": "63f64e71-2ca4-4ac9-a49e-45a1d9531179", "event_type": "COMMENT", "env_id": "c3d2c46e-df9e-40c4-8014-5e8c9fdf3cc1", "author": "Test", "data": {"body": "SUSPENDED: This task (T1 for story 50d5-ac2e \u2014 add plugin boundary constraint to doc-writer.md) was suspended after implementation was started. The done definitions require hardcoding 'plugins/dso/' inside doc-writer.md, which is a distributed plugin file. The implementation is architecturally wrong. Reverted commit 3eacc31c. Story 50d5-ac2e escalated to brainstorm for re-examination."}}