{"timestamp": 1774814745259511000, "uuid": "84ccf7ea-cbff-49cc-a74b-bb93a38d7483", "event_type": "COMMENT", "env_id": "c3d2c46e-df9e-40c4-8014-5e8c9fdf3cc1", "author": "Joe Oakhart", "data": {"body": "AC amendment (gap analysis): Header table row must clarify dso: agents are local plugin agents resolved via plugins/dso/agents/<name>.md, not enabledPlugins lookup. discover-agents.sh extracts 'dso' but won't find it in enabledPlugins \u2014 dso: agents are dispatched directly by orchestrators, not through discover-agents.sh. Suggested row: dso:bot-psychologist | (local plugin agent, resolved via plugins/dso/agents/)"}}