{"author":"Test","data":{"body":"Investigated (debug-everything 2026-04-28): Design approach: add a 'code_version' field to the bug report template capturing the git SHA at filing time. In debug-everything Bug-Fix Mode, before dispatching fix-bug for each ticket, check whether the bug's code_version is an ancestor of HEAD via 'git merge-base --is-ancestor'. If not, add a skip comment and continue. Changes needed: (1) create-bug/SKILL.md (add code_version to template), (2) shared/prompts/bug-report-template.md (add field definition), (3) debug-everything/SKILL.md Bug-Fix Mode (add ancestry check). Leaving open for dedicated sprint."},"env_id":"c3d2c46e-df9e-40c4-8014-5e8c9fdf3cc1","event_type":"COMMENT","timestamp":1777424697639639000,"uuid":"8dd7f25b-3451-4fbe-bf58-b7a025f29d47"}
